xia_sendinblue/__init__.py
xia_sendinblue/sender.cpython-311-darwin.so
xia_sendinblue-0.0.12.dist-info/LICENSE.txt
xia_sendinblue-0.0.12.dist-info/METADATA
xia_sendinblue-0.0.12.dist-info/WHEEL
xia_sendinblue-0.0.12.dist-info/top_level.txt
xia_sendinblue-0.0.12.dist-info/RECORD
