Metadata-Version: 2.1
Name: xia-sendinblue
Version: 0.0.12
Home-page: https://develop.x-i-a.com/docs/xia-sendinblue/0.0.12/index.html
Author: X-I-A
Author-email: admin@x-i-a.com
Requires-Python: >=3.9
License-File: LICENSE.txt
Requires-Dist: requests
Requires-Dist: xia-mail-sender
